instabuy_integration_utils/__init__.py
instabuy_integration_utils/config.py
instabuy_integration_utils/update.py
instabuy_integration_utils/models/IBAddress.py
instabuy_integration_utils/models/IBBuy.py
instabuy_integration_utils/models/IBCheckoutOption.py
instabuy_integration_utils/models/IBClient.py
instabuy_integration_utils/models/IBCoupon.py
instabuy_integration_utils/models/IBErpIntegration.py
instabuy_integration_utils/models/IBOrderProduct.py
instabuy_integration_utils/models/__init__.py
instabuy_integration_utils/utils/IBException.py
instabuy_integration_utils/utils/IBProductsLoadUtil.py
instabuy_integration_utils/utils/IBRequest.py
instabuy_integration_utils/utils/IBSelfUpdate.py
instabuy_integration_utils/utils/IBUtil.py
instabuy_integration_utils/utils/__init__.py
instabuy_integration_utils-1.0.4.dist-info/LICENSE
instabuy_integration_utils-1.0.4.dist-info/METADATA
instabuy_integration_utils-1.0.4.dist-info/WHEEL
instabuy_integration_utils-1.0.4.dist-info/top_level.txt
instabuy_integration_utils-1.0.4.dist-info/RECORD
