Metadata-Version: 2.1
Name: instabuy-integration-utils
Version: 1.0.4
Summary: Instabuy python 3 integration package
Home-page: https://github.com/Instabuy-Ltda/Instabuy-Integration-Package
Author: Instabuy
Author-email: instabuy.dev@gmail.com
Classifier: Programming Language :: Python :: 3
Classifier: License :: OSI Approved :: MIT License
Classifier: Operating System :: OS Independent
Requires-Python: >=3.7
License-File: LICENSE
Requires-Dist: python-dateutil (~=2.8.2)
Requires-Dist: Unidecode (~=1.2.0)
Requires-Dist: requests (~=2.22.0)
